mailmitt/__init__.py
mailmitt/__main__.py
mailmitt/__version__.py
mailmitt/smtp_server.py
mailmitt/utils.py
mailmitt/web_server.py
mailmitt/static/pure-grids-responsive.min.css
mailmitt/static/pure.min.css
mailmitt/templates/index.html
mailmitt-0.0.4.dist-info/DESCRIPTION.rst
mailmitt-0.0.4.dist-info/METADATA
mailmitt-0.0.4.dist-info/RECORD
mailmitt-0.0.4.dist-info/WHEEL
mailmitt-0.0.4.dist-info/entry_points.txt
mailmitt-0.0.4.dist-info/metadata.json
mailmitt-0.0.4.dist-info/top_level.txt
