Metadata-Version: 2.0
Name: mailmitt
Version: 0.0.4
Summary: Simple SMTP server for testing mailing code.
Home-page: https://github.com/trvrm/mailmitt
Author: Trevor Morgan
License: UNKNOWN
Platform: UNKNOWN
Classifier: Development Status :: 3 - Alpha
Classifier: Programming Language :: Python :: 3.5
Classifier: Programming Language :: Python :: 3.6
Requires-Python: >=3.5
Requires-Dist: aiohttp
Requires-Dist: aiosmtpd
Requires-Dist: bottle
